phiskills/grpc/__init__.py
phiskills/grpc/api.py
phiskills.grpc-0.0.1.dist-info/LICENSE
phiskills.grpc-0.0.1.dist-info/METADATA
phiskills.grpc-0.0.1.dist-info/WHEEL
phiskills.grpc-0.0.1.dist-info/top_level.txt
phiskills.grpc-0.0.1.dist-info/RECORD
