Metadata-Version: 2.1
Name: phiskills.grpc
Version: 0.0.1
Summary: Phi Skills Generic gRPC API Server
Home-page: https://github.com/phiskills/grpc-api.py
Author: Phi Skills
Author-email: hello@phiskills.com
License: GNU GPLv3
Project-URL: Company website, https://phiskills.com
Project-URL: Documentation, https://github.com/phiskills/grpc-api.py
Project-URL: Source, https://github.com/phiskills/grpc-api.py
Keywords: Phi Skills gRPC API Server
Platform: UNKNOWN
Classifier: Development Status :: 2 - Pre-Alpha
Classifier: Intended Audience :: Developers
Classifier: License :: OSI Approved :: GNU General Public License v3 (GPLv3)
Classifier: Programming Language :: Python :: 3
Classifier: Topic :: Software Development
Requires-Python: >=3.8, <4
Requires-Dist: grpcio
Requires-Dist: grpcio-health-checking
